Workbook

Sheet 0_说明
A1: ECL4111 文献综合表：2026-10-09 Shawnee 教授一对一精修后
A2: 学生：Jiecheng Yang｜题目：Newcomer Families' Access to and Use of Early Childhood Education and Care Support Resources in Toronto｜截止：2026-10-16 (周五) 11:59 pm
A3: 依据：(1) 会议转录 00:06:55–00:54:25；(2) Google Doc 中教授的 7 条批注和她当场输入的句子；(3) 教授发的三张清单 (Gaps / Thematic Analysis / Conclusion)；(4) 13 篇期刊文献 PDF 逐页核对；(5) 网上核对的新增候选文献。
A5: 工作表
A6: 1_教授建议：31 条意见，每条都有原话、中文解读和具体改法。
A7: 2_新结构：新论点和三个新主题，逐段写清证据、页码、加拿大锚点、删除内容。
A8: 3_现有文献：正文和 References 中出现的 13 篇期刊、4 份政策，以及 3 篇“正文引用但 References 缺条目”的文献，逐篇给出处理决定。
A9: 4_删除清单：要整篇删的文献，以及要删的句子和段落。
A10: 5_新增文献：加拿大、安省、多伦多的候选文献 (已核对书目信息)，标明放在哪个主题、优先级和核验程度。
A11: 6_清单自查：教授三张清单逐项对照当前稿件。
A12: 7_数量核对：用公式自动统计保留后的原始研究、政策文件和总数，并对照作业要求 (≥8 / ≥4 / ≥12)。
A13: 8_引用分布：计划保留的来源在 Intro、Theme 1/2/3、Conclusion 中的分布，检查每个主题是否都有加拿大锚点。
... A29: 网络代理拦截了所有出版社和数据库页面，新增文献只核到检索摘要片段 (Brown 2020、Poureslami 2013、Jang 2020 的书目已在 PDF 参考文献里逐字核对)。本轮网页检索额度已用完；如需继续核对，发下一条消息即可。

Sheet 1_教授建议
A1: 编号 | B1: 时间点 / 批注 | C1: 草稿位置 | D1: 教授原话 (English, 转录原文) | E1: 中文解读 | F1: 修改方案 (具体做法) | G1: 优先级 | H1: 涉及文献
A2: F01 | B2: 10:48 | C2: 全文红字口语句 | D2: "I need you to use more formal language here." | E2: 红字版本 (So..., pretty widespread, the exact same pattern, doesn't even have, ---) 不是学术语体。 | F2: 删除全部红字口语句；以已划线的正式版本为底稿，按新论点改写。不用缩写 (don't, can't)，不用破折号。 | G2: 必改 | H2: 全部
A3: F02 | B3: 11:09-11:24 | C3: Introduction: "This is especially important for newcomer families in Toronto because there are more newcomer children..." | D3: "If you're saying this is especially important for newcomer families, you need a source." | E3: 无来源的判断句。 | F3: 加引用 Toronto Children's Services (2025, p. 27)：newcomer children are Toronto's fastest-growing child population；或删去此句。 | G3: 必改 | H3: Toronto Children's Services (2025)
A4: F03 | B4: 12:31 | C4: Introduction 及全文 | D4: "So just standardize your punctuation too, right?" | E4: 标点不统一。 | F4: 统一：页码范围用 en dash (pp. 75–78)；引号统一；不用破折号；修正 "Canada.The" 一类缺空格。 | G4: 必改 | H4: —
A5: F04 | B5: 12:42-14:31 | C5: Introduction 目的句 "examines how policies are understood and implemented" | D5: "This is not what you're planning to do... it's how newcomer families access... how access is translated to their usage... You're not focused on understanding, you're focused on usage." | E5: 研究目的写成了政策执行研究，偏离家庭层面的 access → use。 | F5: 删去 policy understood / implemented 类目的句；目的句改为家庭层面：newcomer families' understanding and use of services。 | G5: 必改 | H5: Gov. of Canada & Ontario (2022)
A6: F05 | B6: 15:12-15:20 | C6: Introduction 背景句 (教授当场删除) | D6: "Okay, so I don't need this information... This part I don't need... This is the central thing." | E6: 与核心问题无关的背景不要。 | F6: 引言只保留服务新论点的背景：CWELCC → 多伦多新移民家庭 → 理解与使用。 | G6: 必改 | H6: —
A7: F06 | B7: 15:20-17:19；批注 #0 "what type?" | C7: Theme 1 首句 "utilizing resources" | D7: "And then you have to tell me what type of resources too, right?" | E7: 资源类型没有界定。 | F7: 写明资源类型：例如 licensed child care and fee reductions under CWELCC, child care fee subsidies, EarlyON programs, family support resources referred through child care centres；与 RQ 中 "family support resources" 保持一致。 | G7: 必改 | H7: Gov. 2022; Ontario MoE 2023; TCS 2025
A8: F07 | B8: 16:27-25:15；批注 #1 | C8: Theme 1 "they simply don't know what's out there" | D8: "You're focused on people who already have access to the resources or know about them... They know what's out there, but they don't know how what's out there meet their needs." 批注："So you they know what is out there but they do not know how to use them meet their needs" | E8: 不能写“家庭不知道有服务”；要写“知道有服务，但不了解如何用来满足自己的需要”。 | F8: 删去 "they simply don't know what's out there"。改写方向：families may know that a service exists but lack a nuanced understanding of what it offers, whether they qualify, and how to use it to meet their needs。 | G8: 必改 | H8: Burns (2025); Heinz, Bell, et al. (2025)
A9: F08 | B9: 19:31-20:59 | C9: 概念说明 (不写进论文) | D9: "I have access to the community center... I've never used the community center... because I don't know the type of programs that are offered and how those programs meet my needs." / computer example | E9: 用社区中心、电脑两个例子解释 access ≠ use：可得、知道 ≠ 会用来满足需要。 | F9: 作为引言里 access 和 use 定义的思路；不要把教授的例子写进论文。 | G9: 参考 | H9: —
A10: F09 | B10: 25:24-26:08；批注 #2 | C10: Theme 1 Burns 句 | D10: "This is okay because it means... even though they have heard about it, they don't understand how to use it to meet their needs... bring this point here." 批注："Bring this point here to say that it will limit their understanding of how to use these to meet their needs." | E10: Burns 证据保留，但要加一句解释：信息错误或不足会限制家长理解如何使用。 | F10: Burns 句后加 interpretation 句；同时说明 Burns 是一般家长样本，没有单独分析新移民家庭。 | G10: 必改 | H10: Burns et al. (2025, p. 73)
A11: F10 | B11: 26:34-27:35 | C11: Theme 1 New Mexico 句 + "expanding a policy doesn't make parents aware" | D11: "Okay, so I don't need this... this isn't really connected to your main point... And this doesn't also connect to your [point]." | E11: 旧结论“政策扩张不等于知晓”与新论点不连接。 | F11: 删去 "policy expansion alone does not produce parental awareness" 一类结论。Heinz 证据保留，但改写成理解资格和费用的角度 (见 F13)。 | G11: 必改 | H11: Heinz ×2
A12: F11 | B12: 27:54-31:31 (教授在文档里输入，粉色底) | C12: Introduction 论点句 | D12: "Most of what you've written speaks to the fact that the parents, they're not knowledgeable about the benefits... change your thesis statement..." 教授输入："This review explores how newcomer families lack understanding of childcare resources and services limits their utilization and benefit of these services." | E12: 新论点：缺乏对托育资源与服务的理解 → 限制使用与受益。 | F12: 采用新论点并修语法，例如："This review explores how newcomer families' limited understanding of child care resources and services limits their use of and benefit from these services." 全文每段都要回扣这一句。 | G12: 必改 | H12: 全部
... A32: F31 | B32: 53:49-53:55 | C32: 截止日期 | D32: Student: "due date is a Friday for next Friday, right?" Prof: "Yes." | E32: 截止：2026 年 10 月 16 日 (周五) 11:59 pm。 | F32: — | G32: 参考 | H32: —

Sheet 2_新结构
A1: 部分 | B1: 段落功能 (Week 5 结构) | C1: 要写什么 (中文说明) | D1: 可用证据 (已核对页码) | E1: 加拿大 / 安省锚点 | F1: 删掉的内容 | G1: 对应教授意见
A2: 论点 (Thesis) | B2: 全文主线 | C2: 教授当场改写的论点 (F11)，修过语法："This review explores how newcomer families' limited understanding of child care resources and services limits their use of and benefit from these services." 每段都要回扣这一句。 | D2: — | E2: — | F2: 旧论点：policy → institution → family → educator 四段式 | G2: F11, F26
A3: Introduction | B3: 1 大背景 (broad context) | C3: 安省正在推行 CWELCC，让托育更便宜、更容易获得。 | D3: Government of Canada & Government of Ontario (2022) (不写页码) | E3: 联邦与安省协议 | F3: Gagné Petteni 的 BC 入学准备数据 (已划掉) | G3: F04, F05
A4: Introduction | B4: 2 聚焦多伦多新移民 (narrow focus) | C4: 为什么这对多伦多新移民家庭特别重要，必须有来源 (F02)。 | D4: Toronto Children's Services (2025, p. 27)；Ontario Ministry of Education (2023, p. 17 待核) | E4: 多伦多、安省政策 | F4: 无来源的 "there are more newcomer children..." | G4: F02
A5: Introduction | B5: 3 关键概念 (key concepts) | C5: newcomer families 的定义；写明资源类型 (F06)；区分 access 和 use：知道、可得 ≠ 会用来满足需要 (F07, F08)。 | D5: Miles et al. (2026, p. 186) 定义 | E5: 资源类型用安省名称：CWELCC fee reductions、fee subsidies、EarlyON | F5: "resources" 不写类型 | G5: F06, F07, F08
A6: Introduction | B6: 4 缺口预告 + 目的 + 主题预告 | C6: 论点句，再加三个主题的预告 (用三个新主题名)。 | D6: — | E6: — | F6: "examines how policies are understood and implemented" | G6: F04, F11
A7: Theme 1：Newcomer Families Lack a Nuanced Understanding of How to Use Services | B7: Topic sentence | C7: 教授句修语法：newcomer families may know that services exist, but they lack a nuanced understanding of what the services offer, whether they qualify, and how to use them to meet their needs。 | D7: — | E7: — | F7: "they simply don't know what's out there" (F07) | G7: F07, F12
A8: Theme 1 | B8: Evidence 1 (加拿大) | C8: 多数家长听说过 CWELCC，但许多人信息错误、有限或没有 → 加解释句：这限制了家长理解如何使用 (F09)。写明一般样本。 | D8: Burns et al. (2025, p. 73) | E8: 加拿大四省 | F8: — | G8: F09
A9: Theme 1 | B9: Evidence 2 + 3 (不点名国家) | C9: 刚到的家庭不了解早期服务体系，不知道 copay 已免，听说过却以为自己不合格；有些家庭按过时的收入标准被告知不合格。 | D9: Heinz, Bell, et al. (2025, pp. 398, 400)；Heinz, Nava, et al. (2025, pp. 4–5) | E9: 多伦多锚点：Toronto Children's Services (2025) 中家长难以理解 EarlyON、托育和补贴资格的信息 (须在 PDF 里核页码)；可加 Ajayi et al. (2026) 的安省证据 (须先读全文) | F9: New Mexico、400% FPL、"exact same pattern" | G9: F10, F13
A10: Theme 1 | B10: Contrast / connection | C10: 比较：加拿大一般样本 vs 新移民样本，都显示“听说过 ≠ 理解如何使用”。可加一句：错过报名期也说明不了解制度。 | D10: Loudová Stralczynská et al. (2025, p. 8) (可选) | E10: — | F10: Fakhari 2025 许可证、经费句；Papakosma 机构段；Zamanbin 全部 | G10: F14, F15
A11: Theme 1 | B11: Takeaway | C11: 理解不足限制使用和受益 → 自然过渡到 Theme 2：需要有人帮忙理解。 | D11: — | E11: — | F11: "Understanding how policy reaches children..."、"Implementation requires..." | G11: F15
A12: Theme 2：Newcomer Families Need Support to Use These Services | B12: Topic sentence (教授输入) | C12: "Newcomer families need intermediaries who can help them use the services. When supports such as interpreters and navigators are provided for newcomer families, they are better able to use services (Fakhari et al., 2023; Fakhari et al., 2025; Schwartz et al., 2026)." | D12: 三篇放在括号里 (F16) | E12: 两篇加拿大 + 一篇国际 | F12: "which as" (改 such as) | G12: F16
... A25: Researcher Reflection | B25: 5–8 句 | C25: Parkdale 实习、QR 码资源区 → 读文献后改变的认识：资源存在 ≠ 家庭会用；Fakhari (2023) 的手写注册说明影响最大。和新论点保持一致。 | D25: Fakhari et al. (2023, p. 8) | E25: 多伦多 Parkdale | F25: 两个版本并存 (只留一个) | G25: —

Sheet 3_现有文献
A1: 编号 | B1: 文献 (正文引用格式) | C1: 类型 | D1: 国家 / 地区 | E1: 样本 / 对象 | F1: 新移民样本? | G1: 当前草稿出现位置 | H1: 已核对证据与页码 (PDF 已读) | I1: 与新论点契合度 | J1: 相关教授意见 | K1: 处理决定 | L1: 新位置 | M1: 具体用法 (中文) | N1: 国家名处理 | O1: References 状态 | P1: 核验状态 | Q1: 计数类别 | R1: 最终计入?
A2: S01 | B2: Burns et al. (2025) | C2: 原始研究 · 问卷 | D2: 加拿大 (ON, QC, BC, AB) | E2: 1,341 名家长 (一般样本) | F2: 否 (一般样本) | G2: Intro; Theme 1; Conclusion | H2: p. 73: 18.49% 知道 CWELCC 正在实施；39.08% 信息错误、有限或没有信息。pp. 75–76: 省份、种族、人口密度、孩子年龄差异。p. 78: 性别与收入差异。 | I2: 高 | J2: F09 | K2: 保留·核心 | L2: Theme 1 (Intro 可选) | M2: Theme 1 第一条证据：多数家长听说过 CWELCC，但 39.08% 信息错误、有限或没有 (p. 73)。后面加一句解释 (F09)：这会限制家庭理解如何使用服务来满足需要。要写明这是一般家长样本，没有单独分析新移民。 | N2: 加拿大，可写 "in four Canadian provinces" | O2: 已列入 | P2: PDF 已读 | Q2: 原始研究 | R2: 是
A3: S02 | B3: Fakhari et al. (2023) | C3: 原始研究 · 照片发声 (photovoice) | D3: 加拿大 (Halifax, NS) | E3: 8 名讲阿拉伯语的新移民家庭成员 + 6 名 ECE | F3: 是 | G3: Theme 2 (旧); Theme 3 (旧); Conclusion; Reflection | H3: p. 7: 家庭更愿意使用尊重文化差异的项目。p. 8: 多数依靠面对面联系或带回家的传单；服务人员手写注册说明。p. 10: 新移民家庭信任服务人员后才会去获取信息和资源；来自可信社交圈的信息最有用，因为常用他们的首选语言。 | I3: 高 | J3: F20, F22, F24 | K3: 保留·核心 | L3: Theme 2 + Theme 3 + Reflection | M3: Theme 2：服务人员和可信的社交网络帮助家庭理解并完成注册 (pp. 8, 10)。Theme 3：尊重文化差异的项目，家庭更愿意使用 (p. 7)。这是现有文献里最重要的加拿大新移民家庭证据。 | N3: 加拿大，可保留 "in Nova Scotia" | O3: 已列入 | P3: PDF 已读 (印刷页 = PDF 页 − 1) | Q3: 原始研究 | R3: 是
A4: S03 | B4: Fakhari et al. (2025) | C4: 原始研究 · 全国扫描 + 访谈 | D4: 加拿大 (全国 38 个安置机构托育项目) | E4: 安置机构的服务提供者 | F4: 部分 (服务新移民家庭；受访者是服务提供者) | G4: Theme 1 (旧：许可证、经费、人员) | H4: p. 84: 33/38 个项目设资格条件 (如移民身份)。pp. 87–88: 许可证与经费限制。p. 90: 文化和语言多样的教育者 "enhanced the experiences of immigrant families and their children when accessing child care programs"；"a culturally responsive, inclusive environment"。p. 91: 语言课 (LINC)、托育与口译服务合作 "helps clients to understand and experience the breadth of services"。 | I4: 原用法：低 → 改用后：高 | J4: F14 | K4: 改用 (删旧句，换用途) | L4: Theme 2 + Theme 3 | M4: 删除许可证、经费、人员那句 (F14)。Theme 2 用 p. 91：语言课、托育和口译服务的合作帮助家庭理解有哪些服务。Theme 3 用 p. 90：文化和语言多样的教育者营造文化回应的环境。要写明这是服务提供者的观点。 | N4: 加拿大 | O4: 已列入 | P4: PDF 已读 (pp. 90–91 本次新核) | Q4: 原始研究 | R4: 是
A5: S04 | B5: Finno-Velasquez et al. (2025) | C5: 原始研究 · 问卷 | D5: 美国 (新墨西哥州边境) | E5: 227 名移民照护者 | F5: 是 | G5: Theme 2 (旧); Theme 3 (旧) | H5: p. 8: 32.6% 用过补贴，34.4% 用过正规托育。p. 5: help-seeking 量表测的是对专业心理帮助的态度。p. 10: 横断面设计，可能存在反向因果。 | I5: 低–中 | J5: F23, F28 | K5: 删除 (或只在 Conclusion 用一次) | L5: Conclusion (可选) | M5: 正文主题段删除：美国研究，测的是单一时间点的使用，不是理解 → 使用。若要支撑缺口“多数研究只看单一时间点”(F28)，可在结论里用一次 (p. 10)；否则连同 References 一起删。 | N5: 不点名 | O5: 已列入 (若删须同步删) | P5: PDF 已读 | Q5: 原始研究 | R5: 否
A6: S05 | B6: Heinz, Bell, et al. (2025) | C6: 原始研究 · 访谈 / 焦点小组 | D6: 美国 (新墨西哥州) | E6: 原住民、移民、难民、西语家庭 | F6: 是 (部分) | G6: Theme 1; Theme 2 (教授输入的句子); Conclusion | H6: p. 398: 有人听说过补贴项目但以为自己不合格；了解补贴的途径零散，多从亲友或服务提供者那里听说。p. 400: 刚到美国的家庭 "did not understand the early childhood system"；托育系统 "complicated and hard to understand"；安置导航员的帮助参差不齐，有的没把家庭连接到服务；申请表没有家庭的语言版本，连帮忙的英语志愿导航员也觉得难懂；西语家庭不知道多数 copay 已被免除。 | I6: 高 | J6: F13, F16, F17 | K6: 保留·核心 | L6: Theme 1 + Theme 2 | M6: Theme 1：新移民不了解早期服务体系，不知道 copay 已免，听说过却以为自己不合格 (pp. 398, 400)，这正是教授的论点。Theme 2：导航员有帮助但不稳定，连导航员也看不懂表格 (p. 400)。引用必须写 Heinz, Bell, et al. (2025)，不能写 Bell et al.。 | N6: 删去 "New Mexico" | O6: 已列入 | P6: PDF 已读 (印刷页 = PDF 页 + 392) | Q6: 原始研究 | R6: 是
A7: S06 | B7: Heinz, Nava, et al. (2025) | C7: 原始研究 · 混合方法 | D7: 美国 (新墨西哥州) | E7: 通过 WIC 招募的家长 (一般样本) | F7: 否 | G7: Theme 1; Conclusion | H7: p. 2: 补贴资格到 400% FPL，没有等候名单。pp. 4–5: 6 名未使用者在 2021 年扩大资格前申请，被告知不合格。p. 4 Table 2: 35% (n = 12) 的未使用者不知道有补贴。 | I7: 中 | J7: F13 | K7: 保留·压缩 | L7: Theme 1 | M7: Theme 1 用一句：有些家庭按过时的收入标准被告知不合格，之后没有再申请 (pp. 4–5)。写明不是新移民样本。⚠ 现稿把 Nava 的 400% FPL 和无等候名单 (p. 2) 与 Bell 的“移民、难民、西语家长不知道自己合格”(pp. 398, 400) 混成一个 "Heinz et al. (2025)"，必须拆成两个引用。 | N7: 删去 "New Mexico" | O7: 已列入 | P7: PDF 已读 | Q7: 原始研究 | R7: 是
A8: S07 | B8: Lee et al. (2026) | C8: 原始研究 · 质性 | D8: 美国 (密苏里州) | E8: 移民母亲 (WIC 营养项目) | F8: 是 | G8: 正文未引用 (只在 References) | H8: Sub-themes 1.1–1.3：学习成本、合规成本 (无页码)。 | I8: 低 (WIC 不是托育资源) | J8: F23 | K8: 删除 | L8: — | M8: 正文没有引用，References 里多出一条；内容是营养项目，与托育资源无关。直接从 References 删除。 | N8: — | O8: 从 References 删除 | P8: PDF 已读 | Q8: 原始研究 | R8: 否
A9: S08 | B9: Loudová Stralczynská et al. (2025) | C9: 原始研究 · 质性 | D9: 捷克 | E9: 15 名乌克兰难民母亲 | F9: 是 | G9: Theme 2 (旧); Theme 3 (旧); Conclusion | H9: p. 7: 邻居、亲戚帮忙找学校和托育。p. 8: 社区中心和 NGO 帮助了解复杂的入园制度；入园要打几个月电话、跑多所幼儿园；常错过 5 月报名期。pp. 9–10: 有尊重家庭的老师，也有幼儿园反复叫家长来接孩子，不考虑单亲家长的工作。 | I9: 中 | J9: F20, F23 | K9: 保留·压缩 | L9: Theme 2 (Theme 3 可选) | M9: Theme 2：邻居、社区中心和 NGO 帮助家庭理解复杂的入园流程 (pp. 7–8)；错过报名期说明不了解制度 (p. 8)。Theme 3 (可选)：老师是否顾及家庭处境 (pp. 9–10)。不写捷克或乌克兰。 | N9: 删去 "Czech" "Ukrainian" | O9: 已列入 | P9: PDF 已读 (印刷页 = PDF 页 − 1) | Q9: 原始研究 | R9: 是
A10: S09 | B10: Lund (2024) | C10: 原始研究 · 质性 | D10: 挪威 | E10: 12 名难民家长 + ECE 专业人员 | F10: 是 | G10: Theme 3 (旧, 2 处) | H10: p. 7: 口译员每年只在 3–4 次会议时提供。p. 8: 家长希望孩子学挪威语，同时了解本族文化。p. 9: 一位母亲想要监控摄像头。 | I10: 中 | J10: F22, F23 | K10: 保留·压缩 | L10: Theme 2 + Theme 3 | M10: Theme 2：口译只在每年 3–4 次会议时提供，支持不足 (p. 7)。Theme 3：家长希望孩子学新语言，也保有本族文化 (p. 8)。删去监控摄像头的例子。 | N10: 删去 "Norway" "Norwegian" | O10: 已列入 | P10: PDF 已读 | Q10: 原始研究 | R10: 是
A11: S10 | B11: Lund (2026) | C11: 原始研究 · 质性 | D11: 挪威 | E11: 移民家长 (含一位美国父亲) | F11: 是 | G11: Theme 3 (旧, 3 处) | H11: p. 10: 家长等有口译的会议才谈问题。pp. 10–11: 美国父亲谈孩子睡眠问题的合作。p. 13: "belonging is conditional and unevenly distributed"；正式获得服务并不保证被接纳。 | I11: 中 | J11: F21, F23 | K11: 保留·压缩 (篇幅紧可删) | L11: Theme 3 (1 句) | M11: 只留 p. 13 一句：获得服务不等于被接纳，因此服务需要更有回应性。删去美国父亲例子和“未说出的需要”这条线 (F21)。与 Lund (2024) 同作者同国家，篇幅超时优先删这篇。 | N11: 删去 "Norway" | O11: 已列入 | P11: PDF 已读 | Q11: 原始研究 | R11: 是
A12: S11 | B12: Miles et al. (2026) | C12: 综述 · 范围综述 (scoping review) | D12: 以美国研究为主 (含 3 篇加拿大研究) | E12: 38 项研究 (33 篇检索 + 5 篇参考文献追溯) | F12: 是 | G12: Introduction (定义); Conclusion | H12: p. 186: "Newcomer families, including refugees and immigrants"。p. 191: 用家庭母语做宣传、家长或社区联络人 (liaisons)。p. 193: "Sixty-eight percent of studies discussed strategies supporting acceptability related to program responsiveness"，包括聘请口译员、文化和语言匹配的员工。p. 202: 对相关因素了解有限。纳入的加拿大研究：Fakhari et al. (2023)、Jang (2020)、Poureslami et al. (2013)。 | I12: 高 | J12: F16, F22, F28 | K12: 保留·核心 (扩大用途) | L12: Intro + Theme 2 + Theme 3 + Conclusion | M12: Intro：newcomer 定义 (p. 186)。Theme 2：社区联络人、口译员 (pp. 191, 193)。Theme 3：68% 的研究提到提高服务回应性 (p. 193)。Conclusion：缺口 (p. 202)。⚠ 综述，不计入“原始研究 ≥ 8 篇”。 | N12: 不需要国家名 | O12: 已列入 | P12: PDF 已读 (印刷页 = PDF 页 + 184) | Q12: 综述 | R12: 是
... A21: X3 | B21: Ajayi et al. (2026) | C21: 原始研究 · 质性 | D21: 加拿大 (安省 Kingston 与 London) | E21: 25 名黑人家长 | F21: 未确认 | G21: Theme 2 (旧, 1 处) | H21: 全文未读。之前上传的 "Ajayi" 文件实为 Ricciardi & Winsler (2024)。检索片段：纳入条件是 "English-speaking Black parents and caregivers 18 years of age and older who had children 5 years old or younger ... and used ELCC services in Kingston or London"；四个主题：系统性障碍、缺乏信息与社区支持、托育场所的文化不敏感、经济困难。参考文献 (片段)：Ajayi, M., Siiba, A., Kangmennaang, J., Macdonald, D., & Luginaah, I. (2026). "I'm appalled and astonished": Experiences of Black parents and caregivers navigating early learning and childcare in Kingston and London, Ontario. Journal of Childhood Studies, 51(1), [页码 NOT VERIFIED]. https://doi.org/10.18357/jcs511202622373 (DOI 未解析) | I21: 高 (安省；但未确认是否含新移民) | J21: F24 | K21: 待核 → 很可能保留 | L21: Theme 1 (信息) + Theme 3 (文化不敏感) | M21: 安省研究，正好回答教授 "What is the literature saying about newcomer families in Canada?"。须先下载正确 PDF (开放获取：journals.uvic.ca/index.php/jcs/article/download/22373/10382)，核对样本是否包含移民家长，再补 References。样本是使用过托育的黑人家长：除非全文写明有新移民，否则只能写 "Black families in Ontario"，不能写成新移民研究。 | N21: 安省可保留 | O21: 未列入 (正文引用却缺条目) | P21: 全文未读 | Q21: 原始研究 | R21: 待定

Sheet 4_删除清单
A1: 编号 | B1: 删除类型 | C1: 对象 | D1: 草稿中的原文 (开头或要点) | E1: 原因 | F1: 依据
A2: D01 | B2: 整篇文献 | C2: Lee et al. (2026) | D2: 只在 References 中，正文没有引用 | E2: 多出来的参考文献条目；WIC 是营养项目，不是托育资源 | F2: F23；APA 正文与参考文献要一一对应
A3: D02 | B3: 整篇文献 | C3: Zamanbin et al. (2026) | D3: "Rather than contradicting these findings, Zamanbin et al. (2026) locate the barrier at a different level..." (出现两次) | E3: 教授判定与论点无关并当场删除；本来也不在 References | F3: F15
A4: D03 | B4: 整篇文献 (建议) | C4: Bhattashali et al. (2026) | D4: "Nine early educators in U.S. Midwestern public preschools reported language barriers..." | E4: 美国研究、教育者视角；References 缺条目。若保留，须补 References (见“现有文献”X2) | F4: F23
A5: D04 | B5: 整篇文献 (建议) | C5: Finno-Velasquez et al. (2025) | D5: "In their survey of 227 immigrant caregivers in New Mexico's borderlands, 32.6%..." | E5: 美国研究；测的是单一时间点的使用，不是理解 → 使用。只有在结论里用来说明“单一时间点”时才保留 | F5: F23, F28
A6: D05 | B6: 整篇文献 (篇幅紧时) | C6: Lund (2026) | D6: Theme 3 中 3 处 | E6: 与 Lund (2024) 同作者同国家；新结构里只需要 p. 13 一句 | F6: F23, F25
A7: D06 | B7: 句子 | C7: Introduction | D7: "So I want to look at how the policy actually reaches families... Right now I think I can organize the literature into three parts..." | E7: 第一人称口语；研究目的偏向政策执行 | F7: F01, F04
A8: D07 | B8: 句子 | C8: Introduction | D8: "I also started to think that knowing about or finding a resource is not the same as actually using it." | E8: 口语化；改为正式的 access 与 use 定义句 | F8: F01, F07
A9: D08 | B9: 句子 | C9: Theme 1 | D9: "So the very first barrier newcomers families can run into happens before they even use any service, they simply don't know what's out there." | E9: 与新论点相反：家庭知道有服务，但不知道如何用 | F9: F07 (批注 #1)
A10: D09 | B10: 句子 | C10: Theme 1 | D10: "Now, Burns et al. didn't look at newcomer families separately, but Heinz et al. (2025) found the exact same pattern in a totally different system. New Mexico offers subsidies..." | E10: 口语；点名州；把 Heinz, Nava (400% FPL、无等候名单，p. 2) 和 Heinz, Bell (移民、难民、西语家长不知道自己合格，pp. 398, 400) 混成一个引用 | F10: F01, F10, F23；引用不符
A11: D10 | B11: 句子 | C11: Theme 1 | D11: "So putting these together, expanding a policy on its own doesn't automatically make parents aware of it." | E11: 旧结论 (政策扩张 ≠ 知晓)，与新论点不连接 | F11: F10
A12: D11 | B12: 段落 | C12: Theme 1 | D12: "Then there's a second group of studies looking at how institutions actually turn policy into services... Fakhari et al. (2025) provide the most direct Canadian evidence: ... licensing, funding, and workforce conditions..." | E12: 机构执行层面；教授说 "this sentence does not connect with that thesis statement" | F12: F14
... A23: D22 | B23: 全文替换 | C23: 国家名和州名 | D23: Norway / Norwegian、Israel / Israeli、Czech / Ukrainian、Swedish、New Mexico、Dutch、U.S. Midwestern | E23: 改成不点名，或写 "studies with refugee families in other countries"；加拿大地名可以保留 | F23: F23 (批注 #5)

Sheet 5_新增文献
A1: 编号 | B1: 优先级 | C1: 计数类别 | D1: APA 7 参考文献 (未核部分标 NOT VERIFIED) | E1: 国家 / 城市 | F1: 建议放置位置 | G1: 支持什么 (具体用法) | H1: 核验程度 | I1: 交稿前必须补核 | J1: 开放获取 / 链接 | K1: 线索来源 | L1: 计划采用? (须先读全文)
A2: N01 | B2: A 强烈建议 | C2: 综述 | D2: Brown, A., McIsaac, J.-L. D., Reddington, S., Hill, T., Brigham, S., Spencer, R., & Mandrona, A. (2020). Newcomer families' experiences with programs and services to support early childhood development in Canada: A scoping review. Journal of Childhood, Education & Society, 1(2), 182–215. https://doi.org/10.37291/2717638X.20201249 | E2: 加拿大 (全国综述；作者在 Halifax) | F2: Intro + Theme 3 + Conclusion | G2: 教授推荐的文献，直接回答 "What is the literature saying about newcomer families in Canada?"。摘要：综述 2000–2019 年 34 篇加拿大研究，归纳三点：跨文化理解、回应与沟通是充分获得服务的关键；部分家庭面临因移民身份加剧的系统性障碍；家庭的看法和社会支持影响他们如何获得和体验服务。可用作引言的“加拿大文献概况”和 Theme 3 的加拿大锚点。 | H2: 书目：已在 Fakhari et al. (2025) 全文参考文献中逐字核对。内容：摘要片段。 | I2: 读全文 (开放获取)，核对引语和页码；可从它的 34 篇里找安省或多伦多的原始研究。 | J2: https://www.j-ces.com/index.php/jces/article/view/49 | K2: 教授推荐；Fakhari 2025 与 Miles 2026 的参考文献 | L2: 是
A3: N02 | B3: A 强烈建议 | C3: 政策 | D3: Ontario Ministry of Education. (2014). How does learning happen? Ontario's pedagogy for the early years. Queen's Printer for Ontario. https://files.ontario.ca/edu-how-does-learning-happen-en-2021-03-23.pdf | E3: 安省 | F3: Theme 3 (可替代 StatCan 作为第 4 份政策) | G3: 安省早期教育的教学法框架；belonging 是四个基础之一。片段："Families should feel that they belong, are valuable contributors to their children's learning, and deserve to be engaged in a meaningful way." 用作 Theme 3 的安省政策标准：服务应回应家庭的文化和语言；研究显示这一标准并不总能做到。 | H3: 标题和 URL：检索结果。引语：片段。页码未核。 | I3: 下载 PDF，核对引语和页码；确认出版者写法。 | J3: 同左 URL | K3: 检索 (Theme 3) | L3: 是
A4: N03 | B4: A 强烈建议 | C4: 政策 | D4: Toronto Children's Services. (2025). Family focus groups: Report back summary. City of Toronto. https://www.toronto.ca/wp-content/uploads/2025/09/90fa-tcs-policy-serviceplan-family-focus-groups.pdf (年份、标题 NOT VERIFIED) | E4: 多伦多 | F4: Theme 1 + Theme 2 | G4: 9 个焦点小组，104 名家长和照护者；刻意招募没有使用服务的家庭，包括新移民家庭。片段：关于 child care、EarlyON 和 fee subsidy 的信息不够、不清楚，也没有多语言版本。可作多伦多本地证据：知道有服务 ≠ 理解如何使用 (Theme 1)；缺少语言和信息支持 (Theme 2)。这是目前找到的最贴合教授论点的多伦多证据。 | H4: 检索摘要片段 (snippet)，全文未读，页码未核 | I4: 先打开已引用的 Toronto Children's Services (2025) 服务规划，看里面是否已有同样的家长意见；若有，直接用已引用的那份，不必新增一条。若两份都引用，APA 要写成 2025a 和 2025b。 | J4: 同左 URL | K4: 检索 (Intro/Theme 1, Theme 2) | L4: 待定
A5: N04 | B5: B 建议 | C5: 原始研究 | D5: Massing, C., Gyan, C., Giesbrecht, C., Kikulwe, D., & Ghadi, N. (2023). Preferences and challenges in access to childcare programs: A mixed-methods study with newcomers to Canada. International Journal of Early Childhood. https://doi.org/10.1007/s13158-023-00375-w (作者顺序、卷期页码、年份 NOT VERIFIED) | E5: 加拿大 (Regina, SK) | F5: Theme 1 + Theme 3 | G5: 新移民专门样本：问卷 305 名到加拿大不满 5 年的新移民 (153 人有孩子)，加 13 个焦点小组共 96 人。片段：47% 没有可用的补贴托育；61.3% 认为项目对其语言和文化不敏感；新移民因 "linguistic, cultural, and administrative barriers" 处于不利。Theme 1：行政和语言障碍；Theme 3：加拿大新移民样本中多数认为项目缺乏文化与语言回应 (数字须核)。 | H5: 检索摘要片段 (snippet)，全文未读，页码未核 | I5: 读全文核对数字；确认年份 (2023 网络首发 / 2024 出刊) 与卷期页码。 | J5: — | K5: 检索 (Theme 1, Theme 2) | L5: 待定
A6: N05 | B6: B 建议 | C6: 原始研究 | D6: Yohani, S., Kirova, A., Georgis, R., Gokiert, R., Mejia, T., & Chiu, Y. (2019). Cultural brokering with Syrian refugee families with young children: An exploration of challenges and best practices in psychosocial adaptation. Journal of International Migration and Integration, 20(4), [页码 NOT VERIFIED]. https://doi.org/10.1007/s12134-019-00651-6 | E6: 加拿大西部 (Edmonton 团队) | F6: Theme 2 | G6: 访谈 9 名讲阿拉伯语的文化中介 (cultural brokers)。片段：家庭难以了解卫生、社会和教育系统，因而 "heavy reliance on cultural brokers"；中介把家庭连接到所需支持。这是 Theme 2 最直接的加拿大中介证据。限制：只访谈了中介，没访谈家庭；结果是心理社会适应，不专指 ECEC。 | H6: 检索摘要片段 (snippet)，全文未读，页码未核。⚠ 检索给出的页码 1181–1202 与 Miles 参考文献中 Seibel (2021) JIMI 22(3) 的页码完全相同，疑似混淆，不能用。 | I6: 读全文，核对页码和内容。 | J6: Bath Spa repository (未核) | K6: 检索 (Theme 2) | L6: 待定
A7: N06 | B7: B 建议 | C7: 原始研究 | D7: Massing, C., Kirova, A., & Hennig, K. (2013). The role of first language facilitators in redefining parent involvement: Newcomer families' funds of knowledge in an intercultural preschool program. Canadian Children, 38(2), [页码 NOT VERIFIED]. https://doi.org/10.18357/jcs.v38i2.15445 | E7: 加拿大 (Edmonton, AB) | F7: Theme 2 + Theme 3 | G7: 跨文化幼儿园 (英语加三种家庭语言) 的民族志资料。片段：第一语言辅导员和文化中介连接家庭与幼儿园，把家庭知识带进课程；一般的家长参与方式以欧美规范为准。Theme 2：项目内的中介让家庭得以参与；Theme 3：说明文化回应的服务是什么样子。“cultural brokers” 是该研究自己的用词，不要拿来当主题名。 | H7: 检索摘要片段 (snippet)，全文未读，页码未核。刊在 "Invitational Articles" 栏目，是否同行评审 NOT VERIFIED。 | I7: 读全文；确认是否同行评审 (若否，不计入原始研究)。 | J7: journals.uvic.ca/index.php/jcs/article/view/15445 | K7: 检索 (Theme 2, Theme 3) | L7: 待定
A8: N07 | B8: B 建议 | C8: 原始研究 | D8: Poureslami, I., Nimmon, L., Ng, K., Cho, S., Foster, S., & Hertzman, C. (2013). Bridging immigrants and refugees with early childhood development services: Partnership research in the development of an effective service model. Early Child Development and Care, 183(12), 1924–1942. https://doi.org/10.1080/03004430.2013.763252 | E8: 加拿大 (BC, Tri-Cities) | F8: Theme 2 (缺少支持时) + Theme 3 | G8: 讲普通话、粤语、韩语和波斯语的移民和难民家长，社区参与式研究。片段：语言障碍、文化观念和对服务者的负面看法阻碍使用。Miles et al. (2026, p. 198) 转述：家长重视孩子在适应新文化和社区时的社交发展。是 Miles 纳入的 3 篇加拿大研究之一。 | H8: 书目：已在 Miles et al. (2026) 全文参考文献中逐字核对。内容：ERIC 摘要片段加 Miles 转述。 | I8: 读全文。 | J8: ERIC EJ1020896 | K8: Miles 参考文献 + 检索 | L8: 待定
A9: N08 | B9: B 建议 | C9: 原始研究 | D9: Kingsbury, M., Findlay, L., Arim, R., & Wei, L. (2021). Differences in child care participation between immigrant and nonimmigrant families. Journal of Childhood Studies, 46(4), 46–58. https://doi.org/10.18357/jcs464202120123 | E9: 加拿大 (全国；SELCCA 2019 + 移民数据库) | F9: Introduction | G9: 片段："children from immigrant backgrounds were less likely to be in child care"；不使用托育的移民家长更常提到费用。可在引言说明加拿大移民家庭使用托育较少。限制：测的是费用和选择，不是理解。 | H9: 检索摘要片段 (snippet)，全文未读，页码未核 | I9: 读全文核对数字。 | J9: journals.uvic.ca/index.php/jcs/article/view/20123 | K9: 检索 (Intro/Theme 1) | L9: 待定
A10: N09 | B10: C 可选 | C10: 原始研究 | D10: Jang, S. Y. (2020). The pluralist language ideology of Korean immigrant mothers and the English-only principle in early childhood education programs. Language and Education, 34(1), 66–80. https://doi.org/10.1080/09500782.2019.1682598 | E10: 加拿大 (城市未核) | F10: Theme 3 (对比) | G10: 8 名韩国移民母亲。Miles et al. (2026, p. 199) 转述：家长选了全英语项目而不是双语项目，因为孩子在家会继续说韩语。可作为 Theme 3 的对比：文化回应不等于一律提供母语，而是回应家庭自己的语言目标。 | H10: 书目：已在 Miles 参考文献核对。内容：只有 Miles 的转述。 | I10: 读全文；确认城市。 | J10: — | K10: Miles 参考文献 | L10: 待定
A11: N10 | B11: C 可选 | C11: 原始研究 | D11: Khanlou, N., Haque, N., Mustafa, N., Vazquez, L. M., Mantini, A., & Weiss, J. (2017). Access barriers to services by immigrant mothers of children with autism in Canada. International Journal of Mental Health and Addiction, 15(2), 239–259. https://doi.org/10.1007/s11469-017-9732-4 | E11: 多伦多 | F11: Theme 1 (旁证) | G11: 21 名移民母亲。片段："lack of information about the resources available for their children, and this lack of knowledge delayed their access to services"。是自闭症服务，不是 ECEC，只能作旁证。 | H11: 检索摘要片段 (snippet)，全文未读，页码未核 | I11: 读全文。 | J11: PMC5378730 | K11: 检索 (Theme 1) | L11: 待定
A12: N11 | B12: C 可选 | C12: 政策 | D12: Statistics Canada. (2021, July 22). Parents' use of child care services and differences in use by mothers' employment status. Insights on Canadian Society (Catalogue No. 75-006-X). https://www150.statcan.gc.ca/n1/pub/75-006-x/2021001/article/00007-eng.htm (作者 NOT VERIFIED) | E12: 加拿大 | F12: Introduction (可选) | G12: 2017 年 GSS 数据：加拿大出生家长的托育使用率 69%，移民家长 53%。作者把差异解释为就业和多代同住，不是理解不足，所以只能作背景。 | H12: 检索摘要片段 (snippet)，全文未读，页码未核 | I12: 打开网页核对数字和作者。 | J12: 同左 URL | K12: 检索 (Intro) | L12: 待定
... A20: N19 | B20: 线索 (不可引) | C20: 无 | D20: Ontario 托育指引 (Child Care and Early Years guideline) 第 6 章对 inclusive programs 的定义："accessible and responsive to children, parents/guardians and caregivers with varying abilities and cultural, language, socio-economic… backgrounds"。标题和年份 NOT VERIFIED。 | E20: 安省 | F20: Theme 3 (线索) | G20: 若能核到原文，是比 Access and Inclusion Framework 更直接的安省“文化回应”政策依据。 | H20: 仅片段 | I20: 找到原文后再决定。 | J20: efis.fma.csc.gov.on.ca/faab/Child Care/Guidelines/Ch.EN/Chapter6_EN.pdf | K20: 检索 (Theme 3) | L20: 否

Sheet 6_清单自查
A1: 清单 | B1: 检查项 (教授原文) | C1: 引导问题 (教授原文) | D1: 当前稿件状态 | E1: 需要做的修改 | F1: 状态
A2: Gaps | B2: I have a clear understanding of the existing literature. | C2: What do recent studies say about the topic? | D2: 13 篇期刊文献已读 PDF；但加拿大文献少 (Burns, Fakhari ×2)。 | E2: 补 1–3 篇加拿大文献 (Brown 2020 为教授推荐；Ajayi 2026 安省)。 | F2: 部分
A3: Gaps | B3: I have identified what is missing, unclear or underexplored. | C3: What aspects of the topic have not been addressed, are inconsistent or need further investigation? | D3: 现稿缺口是“各阶段分开研究”，与新论点 (理解 → 使用) 不完全对上。 | E3: 缺口改为：多伦多托育中心内，新移民家庭如何在支持下从理解资源走到使用资源 (F28, F29)。 | F3: 待改
A4: Gaps | B4: I can explain the significance of the gap. | C4: Why does this gap matter for research, practice or policy? | D4: 有 TCS (2025, p. 47)。 | E4: 补一句对托育中心实践的意义 (教育者如何支持理解)。 | F4: 部分
A5: Gaps | B5: I have linked the gap to my research question. | C5: How does my study address this gap? | D5: 两版 RQ 并存，用语和论点不一致。 | E5: 只留一版；用 understanding → support → use。 | F5: 待改
A6: Gaps | B6: I have provided evidence from multiple sources. | C6: Have I used recent, relevant and reputable sources to support the gap? | D6: 缺口证据：Miles p. 202；17 篇中没有一篇在多伦多 (已核对)。 | E6: 可加 Brown et al. (2020) 加拿大综述作为“加拿大证据有限”的依据 (须先读)。 | F6: 部分
A7: Gaps | B7: I have positioned my study within the broader literature. | C7: How will my study contribute to existing knowledge? | D7: 结论最后一段有，但写的是旧焦点。 | E7: 改为新论点下的贡献。 | F7: 待改
A8: Thematic | B8: My topic sentence introduces the main idea, not a particular source. | C8: Home-language supports can strengthen multilingual children's learning (Smith, 2022). | D8: 旧 Theme 3 以 "In a Norwegian kindergarten study..." 开头，是以文献开头。 | E8: 三个主题都用观点句开头 (见“新结构”表)。 | F8: 待改
A9: Thematic | B9: I synthesize multiple sources instead of summarizing one source at a time. | C9: Studies suggest that practices vary across settings (Brown, 2021; Jones, 2022; Kim, 2023). | D9: 多处逐篇介绍 (Lund → Lund → Bhattashali → Schwartz)，教授批注 #5 "so singularly"。 | E9: 按观点合并引用，例如 (Fakhari et al., 2023; Schwartz et al., 2026)。 | F9: 待改
A10: Thematic | B10: I support general claims with citations. | C10: Play supports children's cognitive and social development (Miller, 2021). | D10: 引言 "especially important..." 无来源 (F02)；Theme 2 "(list three sources)" 还是占位。 | E10: 补 TCS p. 27；Theme 2 补三篇。 | F10: 待改
A11: Thematic | B11: I paraphrase most ideas in my own words and use quotations sparingly. | C11: Meaningful interaction supports children's learning (Garcia, 2020). | D11: 直接引语不多；红字口语需改成正式改写。 | E11: 删红字；保留 "revolutionary" 等少量引语或改为转述。 | F11: 部分
A12: Thematic | B12: I group studies around a shared point or theme. | C12: Research highlights three connected themes... | D12: 旧主题是 policy / family effort / educators。 | E12: 改为教授的三主题：理解 / 支持 / 文化回应。 | F12: 待改
... A19: Conclusion | B19: I end with a strong, clear closing statement. | C19: Have I provided a final sentence that summarizes the importance of the gap and sets up my study? | D19: 结尾句较长、信息多。 | E19: 一句话：为什么需要研究多伦多新移民家庭如何在支持下理解并使用资源。 | F19: 待改

Sheet 7_数量核对
A1: 来源数量核对 (公式自动计算：改动“3_现有文献”R 列或“5_新增文献”L 列的 是/否/待定，这里会自动更新)
A3: 项目 | B3: 现有文献 (最终计入=是) | C3: 新增文献 (采用=是) | D3: 合计 | E3: 作业要求 | F3: 是否达标 | G3: 说明
A4: 原始研究 (primary peer-reviewed) | B4: =COUNTIFS(3_现有文献!$Q$2:$Q$21,"原始研究",3_现有文献!$R$2:$R$21,"是") -> 10 | C4: =COUNTIFS(5_新增文献!$C$2:$C$20,"原始研究",5_新增文献!$L$2:$L$20,"是") -> 0 | D4: =B4+C4 -> 10 | E4: 8 | F4: =IF(D4>=E4,"达标","不足") -> 达标 | G4: ≥ 8 篇 primary peer-reviewed
A5: 综述 (scoping review) | B5: =COUNTIFS(3_现有文献!$Q$2:$Q$21,"综述",3_现有文献!$R$2:$R$21,"是") -> 1 | C5: =COUNTIFS(5_新增文献!$C$2:$C$20,"综述",5_新增文献!$L$2:$L$20,"是") -> 1 | D5: =B5+C5 -> 2 | F5: — | G5: 不计入原始研究，但计入总数
A6: 政策 / 政府 / 组织文件 | B6: =COUNTIFS(3_现有文献!$Q$2:$Q$21,"政策",3_现有文献!$R$2:$R$21,"是") -> 3 | C6: =COUNTIFS(5_新增文献!$C$2:$C$20,"政策",5_新增文献!$L$2:$L$20,"是") -> 1 | D6: =B6+C6 -> 4 | E6: 4 | F6: =IF(D6>=E6,"达标","不足") -> 达标 | G6: ≥ 4 份 government / organizational / policy
A7: 总数 | B7: =SUM(B4:B6) -> 14 | C7: =SUM(C4:C6) -> 2 | D7: =B7+C7 -> 16 | E7: 12 | F7: =IF(D7>=E7,"达标","不足") -> 达标 | G7: ≥ 12 份；所有来源要附 PDF 或链接
A8: 待定 (尚未决定) | B8: =COUNTIF(3_现有文献!$R$2:$R$21,"待定") -> 2 | C8: =COUNTIF(5_新增文献!$L$2:$L$20,"待定") -> 10 | D8: =B8+C8 -> 12 | G8: 交稿前把“待定”都改成 是 或 否
A9: 加拿大 / 安省 / 多伦多来源 (计入) | B9: =COUNTIFS(3_现有文献!$D$2:$D$21,"加拿大*",3_现有文献!$R$2:$R$21,"是")+COUNTIFS(3_现有文献!$D$2:$D$21,"安省*",3_现有文献!$R$2:$R$21,"是")+COUNTIFS(3_现有文献!$D$2:$D$21,"多伦多*",3_现有文献!$R$2:$R$21,"是") -> 6 | C9: =COUNTIF(5_新增文献!$L$2:$L$20,"是") -> 2 | D9: =B9+C9 -> 8 | G9: 教授：What is the literature saying about newcomer families in Canada? 新增表中的文献都是加拿大来源
A11: 说明：“现有文献”只统计 R 列为“是”的条目；Lund (2026) 若因篇幅删去，把 R 列改成“否”即可看到是否仍达标。

Sheet 8_引用分布
A1: 计划保留的来源在各部分的分布 (✓ = 建议使用；来源是“3_现有文献”L 列和“5_新增文献”F 列)
A3: 来源 | B3: 加拿大? | C3: 状态 | D3: Intro | E3: Theme 1 | F3: Theme 2 | G3: Theme 3 | H3: Conclusion
A4: Burns et al. (2025) | B4: 是 | C4: 现有·是 | D4: ✓ | E4: ✓
A5: Fakhari et al. (2023) | B5: 是 | C5: 现有·是 | F5: ✓ | G5: ✓
A6: Fakhari et al. (2025) | B6: 是 | C6: 现有·是 | F6: ✓ | G6: ✓
A7: Heinz, Bell, et al. (2025) | B7: 否 | C7: 现有·是 | E7: ✓ | F7: ✓
A8: Heinz, Nava, et al. (2025) | B8: 否 | C8: 现有·是 | E8: ✓
A9: Loudová Stralczynská et al. (2025) | B9: 否 | C9: 现有·是 | F9: ✓ | G9: ✓
A10: Lund (2024) | B10: 否 | C10: 现有·是 | F10: ✓ | G10: ✓
A11: Lund (2026) | B11: 否 | C11: 现有·是 | G11: ✓
A12: Miles et al. (2026) | B12: 否 | C12: 现有·是 | D12: ✓ | F12: ✓ | G12: ✓ | H12: ✓
A13: Papakosma (2026) | B13: 否 | C13: 现有·是 | F13: ✓
A14: Schwartz et al. (2026) | B14: 否 | C14: 现有·是 | F14: ✓ | G14: ✓
A15: Government of Canada & Government of Ontario (2022) | B15: 是 | C15: 现有·是 | D15: ✓
A16: Ontario Ministry of Education (2023) | B16: 是 | C16: 现有·是 | D16: ✓
A17: Statistics Canada (2025) | B17: 是 | C17: 现有·待定 | D17: ✓
A18: Toronto Children's Services (2025) | B18: 是 | C18: 现有·是 | D18: ✓ | E18: ✓ | F18: ✓ | G18: ✓ | H18: ✓
A19: Ajayi et al. (2026) | B19: 是 | C19: 现有·待定 | E19: ✓ | G19: ✓
A20: N01 Brown et al. (2020) | B20: 是 | C20: 新增·是 | D20: ✓ | G20: ✓ | H20: ✓
A21: N02 Ontario Ministry of Education (2014) | B21: 是 | C21: 新增·是 | G21: ✓
A22: N03 Toronto Children's Services (2025b) focus groups | B22: 是 | C22: 新增·待定 | E22: ✓ | F22: ✓
A23: N04 Massing, Gyan, et al. (2023) | B23: 是 | C23: 新增·待定 | E23: ✓ | G23: ✓
A24: N05 Yohani et al. (2019) | B24: 是 | C24: 新增·待定 | F24: ✓
A25: N06 Massing, Kirova, & Hennig (2013) | B25: 是 | C25: 新增·待定 | F25: ✓ | G25: ✓
A26: N07 Poureslami et al. (2013) | B26: 是 | C26: 新增·待定 | F26: ✓ | G26: ✓
A27: N08 Kingsbury et al. (2021) | B27: 是 | C27: 新增·待定 | D27: ✓
A28: N09 Jang (2020) | B28: 是 | C28: 新增·待定 | G28: ✓
A29: N10 Khanlou et al. (2017) | B29: 是 | C29: 新增·待定 | E29: ✓
A30: N11 Statistics Canada (2021) | B30: 是 | C30: 新增·待定 | D30: ✓
A31: N15 Toronto precarious-status chapter (2025?) | B31: 是 | C31: 新增·待定 | E31: ✓
A32: 每部分来源数 (只算状态为“是”) | D32: =COUNTIFS(D4:D31,"✓",$C$4:$C$31,"*是") -> 6 | E32: =COUNTIFS(E4:E31,"✓",$C$4:$C$31,"*是") -> 4 | F32: =COUNTIFS(F4:F31,"✓",$C$4:$C$31,"*是") -> 9 | G32: =COUNTIFS(G4:G31,"✓",$C$4:$C$31,"*是") -> 10 | H32: =COUNTIFS(H4:H31,"✓",$C$4:$C$31,"*是") -> 3
A33: 其中加拿大来源数 (只算状态为“是”) | D33: =COUNTIFS(D4:D31,"✓",$B$4:$B$31,"是",$C$4:$C$31,"*是") -> 5 | E33: =COUNTIFS(E4:E31,"✓",$B$4:$B$31,"是",$C$4:$C$31,"*是") -> 2 | F33: =COUNTIFS(F4:F31,"✓",$B$4:$B$31,"是",$C$4:$C$31,"*是") -> 3 | G33: =COUNTIFS(G4:G31,"✓",$B$4:$B$31,"是",$C$4:$C$31,"*是") -> 5 | H33: =COUNTIFS(H4:H31,"✓",$B$4:$B$31,"是",$C$4:$C$31,"*是") -> 2
A34: 若“待定”全部采用，每部分来源数 | D34: =COUNTIF(D4:D31,"✓") -> 9 | E34: =COUNTIF(E4:E31,"✓") -> 9 | F34: =COUNTIF(F4:F31,"✓") -> 13 | G34: =COUNTIF(G4:G31,"✓") -> 15 | H34: =COUNTIF(H4:H31,"✓") -> 3
